skfair/__init__.py
skfair/cli.py
skfair/wrappers.py
skfair/emitters/__init__.py
skfair/emitters/rocrate.py
skfair/extractors/__init__.py
skfair/extractors/data.py
skfair/extractors/env.py
skfair/extractors/metrics.py
skfair/extractors/model.py
skfair/validators/__init__.py
skfair/validators/crate.py
skfair-0.1.0.dist-info/licenses/LICENSE
skfair-0.1.0.dist-info/METADATA
skfair-0.1.0.dist-info/WHEEL
skfair-0.1.0.dist-info/entry_points.txt
skfair-0.1.0.dist-info/top_level.txt
skfair-0.1.0.dist-info/RECORD
